portable_wisdom/__init__.py
portable_wisdom/__version__.py
portable_wisdom/article.py
portable_wisdom/cache.py
portable_wisdom/config.py
portable_wisdom/epub.py
portable_wisdom/source.py
portable_wisdom/transformers.py
portable_wisdom/wisdom.py
portable_wisdom/sources/__init__.py
portable_wisdom/sources/instapaper.py
portable_wisdom/styles/nook-glowlight-3.css
portable_wisdom/tests/__init__.py
portable_wisdom/tests/test_article.py
portable_wisdom/tests/test_cache.py
portable_wisdom/tests/test_source.py
portable_wisdom/tests/test_wisdom.py
portable_wisdom/tmp/.keep
portable_wisdom-1.0.1.dist-info/LICENSE
portable_wisdom-1.0.1.dist-info/METADATA
portable_wisdom-1.0.1.dist-info/WHEEL
portable_wisdom-1.0.1.dist-info/entry_points.txt
portable_wisdom-1.0.1.dist-info/top_level.txt
portable_wisdom-1.0.1.dist-info/RECORD
