Metadata-Version: 2.1
Name: portable_wisdom
Version: 1.0.1
Summary: Generate EPUB files from unread Instapaper articles
Author-email: Jacob Budin <self@jacobbudin.com>
License: MIT
Project-URL: Source, https://github.com/jacobbudin/portable-wisdom
Keywords: cli,ebook,reading,epub,instapaper
Classifier: Development Status :: 5 - Production/Stable
Classifier: Environment :: Console
Classifier: Intended Audience :: End Users/Desktop
Classifier: License :: OSI Approved :: MIT License
Classifier: Natural Language :: English
Classifier: Programming Language :: Python
Classifier: Programming Language :: Python :: 3
Classifier: Programming Language :: Python :: 3.7
Classifier: Programming Language :: Python :: 3.8
Classifier: Programming Language :: Python :: 3.9
Classifier: Programming Language :: Python :: 3.10
Classifier: Programming Language :: Python :: 3.11
Requires-Python: >=3.7
License-File: LICENSE
Requires-Dist: ebooklib >=0.18
Requires-Dist: pillow >=9.4.0
Requires-Dist: requests >=2.21
Requires-Dist: beautifulsoup4 >=4.7.1
Requires-Dist: html5lib >=1.0.1
Requires-Dist: diskcache >=5.4.0
Requires-Dist: readwise-pyinstapaper ==0.2.3
Requires-Dist: emoji >=2.2.0
